nopecha/__init__.py
nopecha/_v1_compat.py
nopecha/api/__init__.py
nopecha/api/_base.py
nopecha/api/_key.py
nopecha/api/_throttle.py
nopecha/api/_validate.py
nopecha/api/aiohttp.py
nopecha/api/httpx.py
nopecha/api/requests.py
nopecha/api/types.py
nopecha/api/urllib.py
nopecha/extension/__init__.py
nopecha/extension/_adapter.py
nopecha/extension/extension.py
nopecha-2.0.0.dist-info/METADATA
nopecha-2.0.0.dist-info/WHEEL
nopecha-2.0.0.dist-info/licenses/LICENSE
nopecha-2.0.0.dist-info/RECORD
