Metadata-Version: 2.3
Name: nopecha
Version: 2.0.0
Summary: API bindings for the NopeCHA CAPTCHA-solving service.
Project-URL: Homepage, https://nopecha.com
Project-URL: Documentation, https://developers.nopecha.com
Project-URL: GitHub Repository, https://github.com/NopeCHALLC/nopecha-python
Author-email: NopeCHA <contact@nopecha.com>
License-File: LICENSE
Classifier: License :: OSI Approved :: MIT License
Classifier: Operating System :: OS Independent
Classifier: Programming Language :: Python :: 3
